setup.py
bdpcrypt/__init__.py
bdpcrypt/cli.py
bdpcrypt/clie.py
bdpcrypt.egg-info/PKG-INFO
bdpcrypt.egg-info/SOURCES.txt
bdpcrypt.egg-info/dependency_links.txt
bdpcrypt.egg-info/entry_points.txt
bdpcrypt.egg-info/top_level.txt