Metadata-Version: 1.1
Name: bdpcrypt
Version: 0.1
Summary: Encrypt and decrypt Sony(TM) Blueray players images
Home-page: UNKNOWN
Author: Jorge Niedbalski R.
Author-email: jnr@pyrosome.org
License: BSD
Keywords: bdpcrypt blueray sony decrypt encrypt encrypt bluray
Platform: UNKNOWN
Classifier: Development Status :: 3 - Alpha
Classifier: Intended Audience :: Developers
Classifier: Operating System :: Unix 
